<root>
	<styles>
        <include src="file://{resources}/styles/custom_game/avalore_hire_queue.css" />
        <!-- <include src="file://{resources}/styles/custom_game/avalore_control_building.css" /> -->
    </styles>
    <scripts>
        <include src="file://{resources}/scripts/custom_game/avalore_hire_queue.js" />
    </scripts>
    <Panel class="HireQueueContainer">
        <Panel id="GoldDisplay" class="TeamGoldContainer">
            <Label id="TeamGold" text="Team Gold" />
            <Label id="SharedGold" text="0" />
        </Panel>
        <!-- <Panel id="HireQueue_Top" class="HireQueue_Top">
            <Label id="TopQueueIcon" text="" />
        </Panel>
        <Panel id="HireQueue_Bot" class="HireQueue_Bot">
            <Label id="BotQueueIcon" text="" />
        </Panel> -->
        <!-- <Button id="control_building" class="ControlBuildingClass">
            <Panel class="Contents">
                <Panel class="CustomIcon"/>
                <Label id="ControlBuildingLabel" text="#ControlBuilding"/>
            </Panel>
        </Button> -->
    </Panel>
    
</root>